MANIFEST.in
README.md
requirements.txt
setup.cfg
setup.py
tox.ini
django_envie/__init__.py
django_envie/admin.py
django_envie/exceptions.py
django_envie/functions.py
django_envie/models.py
django_envie/parsers.py
django_envie/views.py
django_envie.egg-info/PKG-INFO
django_envie.egg-info/SOURCES.txt
django_envie.egg-info/dependency_links.txt
django_envie.egg-info/not-zip-safe
django_envie.egg-info/requires.txt
django_envie.egg-info/top_level.txt
docs/01-testing.rst
docs/02-formatting.rst
docs/03-importing.rst
docs/Makefile
docs/conf.py
docs/index.rst
docs/make.bat
tests/__init__.py
tests/runtests.py
tests/settings.py
tests/test_envs.py
tests/urls.py
tests/wsgi.py