Metadata-Version: 1.1
Name: django-envie
Version: 1.0.0
Summary: A module for Django that allows your app to use environment variables in a file
Home-page: https://github.com/osule/django-envie
Author: Oluwafemi Sule
Author-email: oluwafemisule@outlook.com
License: MIT License
Download-URL: https://github.com/osule/django-envie.git
Platform: UNKNOWN
Classifier: Operating System :: OS Independent
Classifier: Development Status :: 4 - Beta
Classifier: Environment :: Web Environment
Classifier: Framework :: Django
Classifier: Intended Audience :: Developers
Classifier: License :: OSI Approved :: MIT License
Classifier: Programming Language :: Python :: 2.7
Classifier: Programming Language :: Python :: 3
Classifier: Topic :: Software Development :: Libraries :: Python Modules
